functon/__init__.py
functon/core.py
functon/exceptions.py
functon/functions.py
functon/parser.py
functon/statements.py
functon/types.py
functon-0.0.2.dev0.dist-info/WHEEL
functon-0.0.2.dev0.dist-info/METADATA
functon-0.0.2.dev0.dist-info/RECORD
