Metadata-Version: 2.1
Name: functon
Version: 0.0.2.dev0
Summary: True functional programming in Python
Home-page: https://github.com/zhivykh/functon
Author: zhivykh
Author-email: zivih.n@gmail.com
Requires-Python: >=3.10,<4.0
Classifier: Programming Language :: Python :: 3
Classifier: Programming Language :: Python :: 3.10
Project-URL: Repository, https://github.com/zhivykh/functon
